databroker_elasticsearch/__init__.py
databroker_elasticsearch/_version.py
databroker_elasticsearch/brokersearch.py
databroker_elasticsearch/converters.py
databroker_elasticsearch/elasticcallback.py
databroker_elasticsearch/elasticdocument.py
databroker_elasticsearch/elasticindex.py
databroker_elasticsearch/version.py
databroker_elasticsearch-0.0.2.dist-info/LICENSE.txt
databroker_elasticsearch-0.0.2.dist-info/METADATA
databroker_elasticsearch-0.0.2.dist-info/WHEEL
databroker_elasticsearch-0.0.2.dist-info/top_level.txt
databroker_elasticsearch-0.0.2.dist-info/RECORD
