Metadata-Version: 2.1
Name: databroker-elasticsearch
Version: 0.0.2
Summary: Databroker Elasticsearch bridge
Home-page: https://github.com/NSLS-II/databroker-elasticsearch
License: BSD (3-clause)
Platform: UNKNOWN
Classifier: License :: OSI Approved :: BSD License
Classifier: Programming Language :: Python :: 3.6
Classifier: Programming Language :: Python :: 3.7
